[
  {
    "line": 2,
    "elements": [
      {
        "line": 3,
        "name": "Kullanici google sayfasina gider",
        "description": "",
        "type": "background",
        "keyword": "Background",
        "steps": [
          {
            "result": {
              "duration": 10424970700,
              "status": "passed"
            },
            "line": 4,
            "name": "kullanici google sayfasina gider",
            "match": {
              "location": "stepdefinitions.GoogleAramaStepDefinitions.kullanici_google_sayfasina_gider()"
            },
            "keyword": "Given "
          }
        ]
      },
      {
        "start_timestamp": "2020-09-23T09:38:30.693Z",
        "line": 7,
        "name": "TC01_kullanici googleda techproeducation aramasi yapar",
        "description": "",
        "id": "google-arama;tc01-kullanici-googleda-techproeducation-aramasi-yapar",
        "type": "scenario",
        "keyword": "Scenario",
        "steps": [
          {
            "result": {
              "duration": 1395460000,
              "status": "passed"
            },
            "line": 8,
            "name": "arama kutusuna techproeducation yazar",
            "match": {
              "location": "stepdefinitions.GoogleAramaStepDefinitions.arama_kutusuna_techproeducation_yazar()"
            },
            "keyword": "And "
          },
          {
            "result": {
              "duration": 2033457600,
              "status": "passed"
            },
            "line": 9,
            "name": "arama sonuclari sayfasinin basligini kontrol eder",
            "match": {
              "location": "stepdefinitions.GoogleAramaStepDefinitions.arama_sonuclari_sayfasinin_basligini_kontrol_eder()"
            },
            "keyword": "Then "
          }
        ],
        "tags": [
          {
            "name": "@googleArama"
          },
          {
            "name": "@techproeducationArama"
          }
        ]
      },
      {
        "line": 3,
        "name": "Kullanici google sayfasina gider",
        "description": "",
        "type": "background",
        "keyword": "Background",
        "steps": [
          {
            "result": {
              "duration": 1857673700,
              "status": "passed"
            },
            "line": 4,
            "name": "kullanici google sayfasina gider",
            "match": {
              "location": "stepdefinitions.GoogleAramaStepDefinitions.kullanici_google_sayfasina_gider()"
            },
            "keyword": "Given "
          }
        ]
      },
      {
        "start_timestamp": "2020-09-23T09:38:44.711Z",
        "line": 12,
        "name": "TC02_kullanici googleda selenium aramasi yapar",
        "description": "",
        "id": "google-arama;tc02-kullanici-googleda-selenium-aramasi-yapar",
        "type": "scenario",
        "keyword": "Scenario",
        "steps": [
          {
            "result": {
              "duration": 1534663900,
              "status": "passed"
            },
            "line": 13,
            "name": "arama kutusuna selenium yazar",
            "match": {
              "location": "stepdefinitions.GoogleAramaStepDefinitions.arama_kutusuna_selenium_yazar()"
            },
            "keyword": "And "
          },
          {
            "result": {
              "duration": 346787000,
              "status": "passed"
            },
            "line": 14,
            "name": "arama sonuclari sayfasinin sonuc sayisini kontrol eder",
            "match": {
              "location": "stepdefinitions.GoogleAramaStepDefinitions.arama_sonuclari_sayfasinin_sonuc_sayisini_kontrol_eder()"
            },
            "keyword": "Then "
          }
        ],
        "tags": [
          {
            "name": "@googleArama"
          },
          {
            "name": "@seleniumArama"
          }
        ]
      },
      {
        "line": 3,
        "name": "Kullanici google sayfasina gider",
        "description": "",
        "type": "background",
        "keyword": "Background",
        "steps": [
          {
            "result": {
              "duration": 1785034400,
              "status": "passed"
            },
            "line": 4,
            "name": "kullanici google sayfasina gider",
            "match": {
              "location": "stepdefinitions.GoogleAramaStepDefinitions.kullanici_google_sayfasina_gider()"
            },
            "keyword": "Given "
          }
        ]
      },
      {
        "start_timestamp": "2020-09-23T09:38:48.464Z",
        "line": 17,
        "name": "TC03_kullanici googleda darmstadt aramasi yapar",
        "description": "",
        "id": "google-arama;tc03-kullanici-googleda-darmstadt-aramasi-yapar",
        "type": "scenario",
        "keyword": "Scenario",
        "steps": [
          {
            "result": {
              "duration": 1642981100,
              "status": "passed"
            },
            "line": 18,
            "name": "arama kutusuna darmstadt yazar",
            "match": {
              "location": "stepdefinitions.GoogleAramaStepDefinitions.arama_kutusuna_darmstadt_yazar()"
            },
            "keyword": "And "
          },
          {
            "result": {
              "duration": 2802945400,
              "status": "passed"
            },
            "line": 19,
            "name": "arama sonuclarinin ilk linkine tiklar",
            "match": {
              "location": "stepdefinitions.GoogleAramaStepDefinitions.arama_sonuclarinin_ilk_linkine_tiklar()"
            },
            "keyword": "Then "
          }
        ],
        "tags": [
          {
            "name": "@googleArama"
          },
          {
            "name": "@darmstadtArama"
          }
        ]
      }
    ],
    "name": "Google arama",
    "description": "",
    "id": "google-arama",
    "keyword": "Feature",
    "uri": "file:src/test/resources/features/googlearama.feature",
    "tags": [
      {
        "name": "@googleArama",
        "type": "Tag",
        "location": {
          "line": 1,
          "column": 1
        }
      }
    ]
  }
]